quickpbsa/__init__.py
quickpbsa/helpers.py
quickpbsa/pbsa.py
quickpbsa/steps_preliminary/__init__.py
quickpbsa/steps_preliminary/helpers.py
quickpbsa/steps_preliminary/kv_lowlevel.py
quickpbsa/steps_preliminary/preliminary_file.py
quickpbsa/steps_refinement/__init__.py
quickpbsa/steps_refinement/helpers.py
quickpbsa/steps_refinement/improve_steps.py
quickpbsa/steps_refinement/refinement_file.py
quickpbsa/steps_refinement/refinement_lowlevel.py
quickpbsa/trace_extraction/__init__.py
quickpbsa/trace_extraction/from_localization.py
quickpbsa/trace_extraction/from_mask.py
quickpbsa/trace_extraction/helpers.py
quickpbsa/trace_extraction/run_trace_extraction.py
quickpbsa/utilities/__init__.py
quickpbsa/utilities/plot_selection.py
quickpbsa/utilities/stacks.py
quickpbsa-2020.0.1.dist-info/LICENSE
quickpbsa-2020.0.1.dist-info/METADATA
quickpbsa-2020.0.1.dist-info/WHEEL
quickpbsa-2020.0.1.dist-info/top_level.txt
quickpbsa-2020.0.1.dist-info/RECORD
