Metadata-Version: 2.1
Name: quickpbsa
Version: 2020.0.1
Summary: Fast and Complete Photobleaching Step Analysis
Home-page: https://github.com/JohnDieSchere/quickpbsa
Author: Johan Hummert
Author-email: johndieschere@gmail.com
License: GPLv3
Platform: UNKNOWN
Classifier: Development Status :: 3 - Alpha
Classifier: License :: OSI Approved :: GNU General Public License v3 (GPLv3)
Classifier: Programming Language :: Python :: 3
Classifier: Topic :: Scientific/Engineering
Requires-Dist: numpy
Requires-Dist: scipy
Requires-Dist: pandas
Requires-Dist: sympy
Provides-Extra: trace_extraction
Requires-Dist: tifffile ; extra == 'trace_extraction'
Requires-Dist: matplotlib ; extra == 'trace_extraction'
